pygmailsorter/__init__.py
pygmailsorter/__main__.py
pygmailsorter/_version.py
pygmailsorter/local.py
pygmailsorter/base/__init__.py
pygmailsorter/base/database.py
pygmailsorter/base/message.py
pygmailsorter/daemon/__init__.py
pygmailsorter/daemon/__main__.py
pygmailsorter/daemon/daemon.py
pygmailsorter/daemon/shared.py
pygmailsorter/daemon/tasks.py
pygmailsorter/google/__init__.py
pygmailsorter/google/authentication.py
pygmailsorter/google/database.py
pygmailsorter/google/mail.py
pygmailsorter/google/message.py
pygmailsorter/ml/__init__.py
pygmailsorter/ml/database.py
pygmailsorter/ml/encoding.py
pygmailsorter/ml/model.py
pygmailsorter/webapp/__init__.py
pygmailsorter/webapp/__main__.py
pygmailsorter/webapp/app.py
pygmailsorter/webapp/config.py
pygmailsorter/webapp/database.py
pygmailsorter/webapp/googleapi.py
pygmailsorter/webapp/render.py
pygmailsorter/webapp/user.py
pygmailsorter/webapp/wsgi.py
pygmailsorter-0.0.6.dist-info/LICENSE
pygmailsorter-0.0.6.dist-info/METADATA
pygmailsorter-0.0.6.dist-info/WHEEL
pygmailsorter-0.0.6.dist-info/entry_points.txt
pygmailsorter-0.0.6.dist-info/top_level.txt
pygmailsorter-0.0.6.dist-info/RECORD
