Metadata-Version: 2.1
Name: pygmailsorter
Version: 0.0.6
Summary: Assign labels to emails in Google Mail based on their similarity to other emails assigned to the same label.
Home-page: https://github.com/mailsort/pygmailsorter
Author: Jan Janssen
Author-email: jan.janssen@outlook.com
License: BSD
License-File: LICENSE
Requires-Dist: google-api-python-client (>=2.92.0)
Requires-Dist: google-auth (>=2.21.0)
Requires-Dist: google-auth-oauthlib (>=1.0.0)
Requires-Dist: numpy (>=1.25.1)
Requires-Dist: tqdm (>=4.65.0)
Requires-Dist: pandas (>=2.0.3)
Requires-Dist: scikit-learn (>=1.3.0)
Requires-Dist: sqlalchemy (>=2.0.18)
Provides-Extra: webapp
Requires-Dist: gunicorn (>=20.1.0) ; extra == 'webapp'
Requires-Dist: flask (>=2.3.2) ; extra == 'webapp'
Requires-Dist: flask-login (>=0.6.2) ; extra == 'webapp'
